looniplot/__init__.py
looniplot/discretizer.py
looniplot/getch.py
looniplot/layer_assembly.py
looniplot/layer_factory.py
looniplot/looniplot.py
looniplot/multi_series.py
looniplot/options.py
looniplot/param_initializer.py
looniplot/pixel_matrix.py
looniplot/plot_elements.py
looniplot/axis_labels/__init__.py
looniplot/axis_labels/extended_talbot_labels.py
looniplot/axis_labels/label_set.py
bhawick.looniplot-0.0.8.dist-info/METADATA
bhawick.looniplot-0.0.8.dist-info/WHEEL
bhawick.looniplot-0.0.8.dist-info/top_level.txt
bhawick.looniplot-0.0.8.dist-info/RECORD
