Metadata-Version: 2.1
Name: bhawick.looniplot
Version: 0.0.8
Summary: Lightweight plotting to the terminal. 4x resolution via Unicode. This is a fork of Uniplot, please use that library instead.
Home-page: https://github.com/bhawickjain
Author: Bhawick Jain
Author-email: 53153810+BhawickJain@users.noreply.github.com
License: MIT
Project-URL: homepage, https://github.com/bhawickjain
Project-URL: documentation, https://github.com/bhawickjain
Project-URL: repository, https://github.com/bhawickjain
Project-URL: changelog, https://github.com/bhawickjain/looniplot/blob/master/CHANGELOG.md
Keywords: plotting,unicode
Classifier: Programming Language :: Python :: 3.7
Classifier: Programming Language :: Python :: 3.8
Classifier: Programming Language :: Python :: 3.9
Classifier: Programming Language :: Python :: 3.10
Classifier: License :: OSI Approved :: MIT License
Classifier: Operating System :: OS Independent
Requires-Python: >=3.7
Requires-Dist: numpy (>=1.20.0)
Provides-Extra: dev
Requires-Dist: pytest (>=3.7) ; extra == 'dev'
Requires-Dist: check-manifest ; extra == 'dev'
Requires-Dist: twine ; extra == 'dev'
Requires-Dist: tox ; extra == 'dev'
Requires-Dist: black ; extra == 'dev'
Requires-Dist: flake8 ; extra == 'dev'
Requires-Dist: mypy ; extra == 'dev'
